iso3901/__init__.py
iso3901/isrc.py
iso3901/py.typed
iso3901-1.1.0.dist-info/licenses/LICENSE
iso3901-1.1.0.dist-info/WHEEL
iso3901-1.1.0.dist-info/METADATA
iso3901-1.1.0.dist-info/RECORD
