Metadata-Version: 2.4
Name: iso3901
Version: 1.1.0
Summary: Structured parsing of ISRC (International Standard Recording Code), as defined in ISO 3901:2019
Keywords: isrc,recording,sound,metadata,ifpi
Author-email: Abel Cheung <abelcheung@gmail.com>
Requires-Python: >=3.8
Classifier: Development Status :: 5 - Production/Stable
Classifier: Intended Audience :: Developers
Classifier: License :: OSI Approved :: MIT License
Classifier: Programming Language :: Python :: 3
Classifier: Programming Language :: Python :: 3 :: Only
Classifier: Programming Language :: Python :: 3.8
Classifier: Programming Language :: Python :: 3.9
Classifier: Programming Language :: Python :: 3.10
Classifier: Programming Language :: Python :: 3.11
Classifier: Programming Language :: Python :: 3.12
Classifier: Programming Language :: Python :: 3.13
Classifier: Programming Language :: Python :: 3.14
Classifier: Topic :: Multimedia :: Sound/Audio
Classifier: Typing :: Typed
License-File: LICENSE
Requires-Dist: iso3166 ~= 2.0
Requires-Dist: tox ~= 4.0 ; extra == "dev"
Requires-Dist: flit ~= 3.2 ; extra == "dev"
Project-URL: Home, https://github.com/Tagger-phile/py-iso3901
Provides-Extra: dev
